{
  "__schema": {
    "queryType": {
      "name": "Query"
    },
    "mutationType": {
      "name": "Mutation"
    },
    "subscriptionType": {
      "name": "Subscription"
    },
    "types": [
      {
        "kind": "SCALAR",
        "name": "Boolean",
        "description": "The `Boolean` scalar type represents `true` or `false`.",
        "fields": null,
        "inputFields": null,
        "interfaces": null,
        "enumValues": null,
        "possibleTypes": null
      },
      {
        "kind": "OBJECT",
        "name": "Comment",
        "description": "Object to represent a comment",
        "fields": [
          {
            "name": "author",
            "description": "The author of the comment",
            "args": [],
            "type": {
              "kind": "NON_NULL",
              "name": null,
              "ofType": {
                "kind": "SCALAR",
                "name": "String",
                "ofType": null
              }
            },
            "isDeprecated": false,
            "deprecationReason": null
          },
          {
            "name": "comment",
            "description": "The comment text",
            "args": [],
            "type": {
              "kind": "NON_NULL",
              "name": null,
              "ofType": {
                "kind": "SCALAR",
                "name": "String",
                "ofType": null
              }
            },
            "isDeprecated": false,
            "deprecationReason": null
          },
          {
            "name": "createdOn",
            "description": "Creation time of the comment",
            "args": [],
            "type": {
              "kind": "SCALAR",
              "name": "String",
              "ofType": null
            },
            "isDeprecated": false,
            "deprecationReason": null
          },
          {
            "name": "id",
            "description": "The technical id",
            "args": [],
            "type": {
              "kind": "NON_NULL",
              "name": null,
              "ofType": {
                "kind": "SCALAR",
                "name": "ID",
                "ofType": null
              }
            },
            "isDeprecated": false,
            "deprecationReason": null
          },
          {
            "name": "talk",
            "description": "The talk for which the comment is made",
            "args": [],
            "type": {
              "kind": "NON_NULL",
              "name": null,
              "ofType": {
                "kind": "OBJECT",
                "name": "Talk",
                "ofType": null
              }
            },
            "isDeprecated": false,
            "deprecationReason": null
          }
        ],
        "inputFields": null,
        "interfaces": [],
        "enumValues": null,
        "possibleTypes": null
      },
      {
        "kind": "OBJECT",
        "name": "CommentPageableResponse",
        "description": "",
        "fields": [
          {
            "name": "content",
            "description": "The comments",
            "args": [],
            "type": {
              "kind": "LIST",
              "name": null,
              "ofType": {
                "kind": "OBJECT",
                "name": "Comment",
                "ofType": null
              }
            },
            "isDeprecated": false,
            "deprecationReason": null
          },
          {
            "name": "pageInfo",
            "description": "Information of the page",
            "args": [],
            "type": {
              "kind": "NON_NULL",
              "name": null,
              "ofType": {
                "kind": "OBJECT",
                "name": "PageInfo",
                "ofType": null
              }
            },
            "isDeprecated": false,
            "deprecationReason": null
          }
        ],
        "inputFields": null,
        "interfaces": [],
        "enumValues": null,
        "possibleTypes": null
      },
      {
        "kind": "OBJECT",
        "name": "Conference",
        "description": "Object to represent a conference",
        "fields": [
          {
            "name": "city",
            "description": "City where the conference is held",
            "args": [],
            "type": {
              "kind": "SCALAR",
              "name": "String",
              "ofType": null
            },
            "isDeprecated": false,
            "deprecationReason": null
          },
          {
            "name": "id",
            "description": "The technical id",
            "args": [],
            "type": {
              "kind": "NON_NULL",
              "name": null,
              "ofType": {
                "kind": "SCALAR",
                "name": "ID",
                "ofType": null
              }
            },
            "isDeprecated": false,
            "deprecationReason": null
          },
          {
            "name": "name",
            "description": "Name of the conference",
            "args": [],
            "type": {
              "kind": "NON_NULL",
              "name": null,
              "ofType": {
                "kind": "SCALAR",
                "name": "String",
                "ofType": null
              }
            },
            "isDeprecated": false,
            "deprecationReason": null
          },
          {
            "name": "talks",
            "description": "Talks on the conference agenda",
            "args": [],
            "type": {
              "kind": "LIST",
              "name": null,
              "ofType": {
                "kind": "NON_NULL",
                "name": null,
                "ofType": {
                  "kind": "OBJECT",
                  "name": "Talk",
                  "ofType": null
                }
              }
            },
            "isDeprecated": false,
            "deprecationReason": null
          }
        ],
        "inputFields": null,
        "interfaces": [],
        "enumValues": null,
        "possibleTypes": null
      },
      {
        "kind": "SCALAR",
        "name": "ID",
        "description": "The `ID` scalar type represents a unique identifier, often used to refetch an object or as key for a cache. The ID type appears in a JSON response as a String; however, it is not intended to be human-readable. When expected as an input type, any string (such as `\"4\"`) or integer (such as `4`) input value will be accepted as an ID.",
        "fields": null,
        "inputFields": null,
        "interfaces": null,
        "enumValues": null,
        "possibleTypes": null
      },
      {
        "kind": "INPUT_OBJECT",
        "name": "InputComment",
        "description": "Input type for a new Comment",
        "fields": null,
        "inputFields": [
          {
            "name": "author",
            "description": "The id of the author",
            "type": {
              "kind": "NON_NULL",
              "name": null,
              "ofType": {
                "kind": "SCALAR",
                "name": "String",
                "ofType": null
              }
            },
            "defaultValue": null,
            "isDeprecated": false,
            "deprecationReason": null
          },
          {
            "name": "comment",
            "description": "The comment text",
            "type": {
              "kind": "NON_NULL",
              "name": null,
              "ofType": {
                "kind": "SCALAR",
                "name": "String",
                "ofType": null
              }
            },
            "defaultValue": null,
            "isDeprecated": false,
            "deprecationReason": null
          },
          {
            "name": "talkId",
            "description": "The id of the talk",
            "type": {
              "kind": "NON_NULL",
              "name": null,
              "ofType": {
                "kind": "SCALAR",
                "name": "Long",
                "ofType": null
              }
            },
            "defaultValue": null,
            "isDeprecated": false,
            "deprecationReason": null
          }
        ],
        "interfaces": null,
        "enumValues": null,
        "possibleTypes": null
      },
      {
        "kind": "INPUT_OBJECT",
        "name": "InputConference",
        "description": "Input type for a new Conference",
        "fields": null,
        "inputFields": [
          {
            "name": "city",
            "description": "City where the conference is held",
            "type": {
              "kind": "SCALAR",
              "name": "String",
              "ofType": null
            },
            "defaultValue": null,
            "isDeprecated": false,
            "deprecationReason": null
          },
          {
            "name": "name",
            "description": "Name of the conference",
            "type": {
              "kind": "SCALAR",
              "name": "String",
              "ofType": null
            },
            "defaultValue": null,
            "isDeprecated": false,
            "deprecationReason": null
          }
        ],
        "interfaces": null,
        "enumValues": null,
        "possibleTypes": null
      },
      {
        "kind": "INPUT_OBJECT",
        "name": "InputPage",
        "description": "",
        "fields": null,
        "inputFields": [
          {
            "name": "page",
            "description": "The requested page",
            "type": {
              "kind": "NON_NULL",
              "name": null,
              "ofType": {
                "kind": "SCALAR",
                "name": "Long",
                "ofType": null
              }
            },
            "defaultValue": null,
            "isDeprecated": false,
            "deprecationReason": null
          },
          {
            "name": "size",
            "description": "The requested size of the page",
            "type": {
              "kind": "NON_NULL",
              "name": null,
              "ofType": {
                "kind": "SCALAR",
                "name": "Long",
                "ofType": null
              }
            },
            "defaultValue": null,
            "isDeprecated": false,
            "deprecationReason": null
          }
        ],
        "interfaces": null,
        "enumValues": null,
        "possibleTypes": null
      },
      {
        "kind": "INPUT_OBJECT",
        "name": "InputPerson",
        "description": "Input type for a new Person",
        "fields": null,
        "inputFields": [
          {
            "name": "blog",
            "description": "URL to the blog",
            "type": {
              "kind": "SCALAR",
              "name": "String",
              "ofType": null
            },
            "defaultValue": null,
            "isDeprecated": false,
            "deprecationReason": null
          },
          {
            "name": "githubAccount",
            "description": "Github account id",
            "type": {
              "kind": "SCALAR",
              "name": "String",
              "ofType": null
            },
            "defaultValue": null,
            "isDeprecated": false,
            "deprecationReason": null
          },
          {
            "name": "name",
            "description": "Fullname of the person",
            "type": {
              "kind": "SCALAR",
              "name": "String",
              "ofType": null
            },
            "defaultValue": null,
            "isDeprecated": false,
            "deprecationReason": null
          }
        ],
        "interfaces": null,
        "enumValues": null,
        "possibleTypes": null
      },
      {
        "kind": "INPUT_OBJECT",
        "name": "InputTalk",
        "description": "Input type for a new Talk",
        "fields": null,
        "inputFields": [
          {
            "name": "summary",
            "description": "Short summary of the talk",
            "type": {
              "kind": "SCALAR",
              "name": "String",
              "ofType": null
            },
            "defaultValue": null,
            "isDeprecated": false,
            "deprecationReason": null
          },
          {
            "name": "title",
            "description": "Title of the talk",
            "type": {
              "kind": "SCALAR",
              "name": "String",
              "ofType": null
            },
            "defaultValue": null,
            "isDeprecated": false,
            "deprecationReason": null
          }
        ],
        "interfaces": null,
        "enumValues": null,
        "possibleTypes": null
      },
      {
        "kind": "SCALAR",
        "name": "Long",
        "description": "Long type",
        "fields": null,
        "inputFields": null,
        "interfaces": null,
        "enumValues": null,
        "possibleTypes": null
      },
      {
        "kind": "OBJECT",
        "name": "Mutation",
        "description": "",
        "fields": [
          {
            "name": "addComment",
            "description": "Add a new comment",
            "args": [
              {
                "name": "comment",
                "description": "",
                "type": {
                  "kind": "NON_NULL",
                  "name": null,
                  "ofType": {
                    "kind": "INPUT_OBJECT",
                    "name": "InputComment",
                    "ofType": null
                  }
                },
                "defaultValue": null,
                "isDeprecated": false,
                "deprecationReason": null
              }
            ],
            "type": {
              "kind": "OBJECT",
              "name": "Comment",
              "ofType": null
            },
            "isDeprecated": false,
            "deprecationReason": null
          },
          {
            "name": "addConference",
            "description": "Add a new conference",
            "args": [
              {
                "name": "conference",
                "description": "",
                "type": {
                  "kind": "NON_NULL",
                  "name": null,
                  "ofType": {
                    "kind": "INPUT_OBJECT",
                    "name": "InputConference",
                    "ofType": null
                  }
                },
                "defaultValue": null,
                "isDeprecated": false,
                "deprecationReason": null
              }
            ],
            "type": {
              "kind": "OBJECT",
              "name": "Conference",
              "ofType": null
            },
            "isDeprecated": false,
            "deprecationReason": null
          },
          {
            "name": "addPerson",
            "description": "Add a new Person",
            "args": [
              {
                "name": "person",
                "description": "",
                "type": {
                  "kind": "NON_NULL",
                  "name": null,
                  "ofType": {
                    "kind": "INPUT_OBJECT",
                    "name": "InputPerson",
                    "ofType": null
                  }
                },
                "defaultValue": null,
                "isDeprecated": false,
                "deprecationReason": null
              }
            ],
            "type": {
              "kind": "OBJECT",
              "name": "Person",
              "ofType": null
            },
            "isDeprecated": false,
            "deprecationReason": null
          },
          {
            "name": "addSpeakerToTalk",
            "description": "Add a speaker to a talk",
            "args": [
              {
                "name": "speakerId",
                "description": "",
                "type": {
                  "kind": "SCALAR",
                  "name": "Long",
                  "ofType": null
                },
                "defaultValue": null,
                "isDeprecated": false,
                "deprecationReason": null
              },
              {
                "name": "talkId",
                "description": "",
                "type": {
                  "kind": "SCALAR",
                  "name": "Long",
                  "ofType": null
                },
                "defaultValue": null,
                "isDeprecated": false,
                "deprecationReason": null
              }
            ],
            "type": {
              "kind": "OBJECT",
              "name": "Talk",
              "ofType": null
            },
            "isDeprecated": false,
            "deprecationReason": null
          },
          {
            "name": "addTalk",
            "description": "Add a new Talk",
            "args": [
              {
                "name": "talk",
                "description": "",
                "type": {
                  "kind": "INPUT_OBJECT",
                  "name": "InputTalk",
                  "ofType": null
                },
                "defaultValue": null,
                "isDeprecated": false,
                "deprecationReason": null
              }
            ],
            "type": {
              "kind": "OBJECT",
              "name": "Talk",
              "ofType": null
            },
            "isDeprecated": false,
            "deprecationReason": null
          },
          {
            "name": "addTalkToConference",
            "description": "Add a talk to a conference",
            "args": [
              {
                "name": "conferenceId",
                "description": "",
                "type": {
                  "kind": "SCALAR",
                  "name": "Long",
                  "ofType": null
                },
                "defaultValue": null,
                "isDeprecated": false,
                "deprecationReason": null
              },
              {
                "name": "talkId",
                "description": "",
                "type": {
                  "kind": "SCALAR",
                  "name": "Long",
                  "ofType": null
                },
                "defaultValue": null,
                "isDeprecated": false,
                "deprecationReason": null
              }
            ],
            "type": {
              "kind": "OBJECT",
              "name": "Conference",
              "ofType": null
            },
            "isDeprecated": false,
            "deprecationReason": null
          }
        ],
        "inputFields": null,
        "interfaces": [],
        "enumValues": null,
        "possibleTypes": null
      },
      {
        "kind": "OBJECT",
        "name": "PageInfo",
        "description": "",
        "fields": [
          {
            "name": "numberOfElements",
            "description": "Number of elements",
            "args": [],
            "type": {
              "kind": "NON_NULL",
              "name": null,
              "ofType": {
                "kind": "SCALAR",
                "name": "Long",
                "ofType": null
              }
            },
            "isDeprecated": false,
            "deprecationReason": null
          },
          {
            "name": "pageNumber",
            "description": "Page number",
            "args": [],
            "type": {
              "kind": "NON_NULL",
              "name": null,
              "ofType": {
                "kind": "SCALAR",
                "name": "Long",
                "ofType": null
              }
            },
            "isDeprecated": false,
            "deprecationReason": null
          },
          {
            "name": "pageSize",
            "description": "Size of the page",
            "args": [],
            "type": {
              "kind": "NON_NULL",
              "name": null,
              "ofType": {
                "kind": "SCALAR",
                "name": "Long",
                "ofType": null
              }
            },
            "isDeprecated": false,
            "deprecationReason": null
          },
          {
            "name": "totalElements",
            "description": "Total number of elements",
            "args": [],
            "type": {
              "kind": "NON_NULL",
              "name": null,
              "ofType": {
                "kind": "SCALAR",
                "name": "Long",
                "ofType": null
              }
            },
            "isDeprecated": false,
            "deprecationReason": null
          },
          {
            "name": "totalPages",
            "description": "Total number of pages",
            "args": [],
            "type": {
              "kind": "NON_NULL",
              "name": null,
              "ofType": {
                "kind": "SCALAR",
                "name": "Long",
                "ofType": null
              }
            },
            "isDeprecated": false,
            "deprecationReason": null
          }
        ],
        "inputFields": null,
        "interfaces": [],
        "enumValues": null,
        "possibleTypes": null
      },
      {
        "kind": "OBJECT",
        "name": "Person",
        "description": "Object to represent a Person",
        "fields": [
          {
            "name": "blog",
            "description": "URL to the blog",
            "args": [],
            "type": {
              "kind": "SCALAR",
              "name": "String",
              "ofType": null
            },
            "isDeprecated": false,
            "deprecationReason": null
          },
          {
            "name": "githubAccount",
            "description": "Github account id",
            "args": [],
            "type": {
              "kind": "SCALAR",
              "name": "String",
              "ofType": null
            },
            "isDeprecated": false,
            "deprecationReason": null
          },
          {
            "name": "id",
            "description": "The technical id",
            "args": [],
            "type": {
              "kind": "NON_NULL",
              "name": null,
              "ofType": {
                "kind": "SCALAR",
                "name": "ID",
                "ofType": null
              }
            },
            "isDeprecated": false,
            "deprecationReason": null
          },
          {
            "name": "name",
            "description": "Fullname of the person",
            "args": [],
            "type": {
              "kind": "NON_NULL",
              "name": null,
              "ofType": {
                "kind": "SCALAR",
                "name": "String",
                "ofType": null
              }
            },
            "isDeprecated": false,
            "deprecationReason": null
          },
          {
            "name": "talks",
            "description": "Talks given by the person",
            "args": [],
            "type": {
              "kind": "LIST",
              "name": null,
              "ofType": {
                "kind": "NON_NULL",
                "name": null,
                "ofType": {
                  "kind": "OBJECT",
                  "name": "Talk",
                  "ofType": null
                }
              }
            },
            "isDeprecated": false,
            "deprecationReason": null
          }
        ],
        "inputFields": null,
        "interfaces": [],
        "enumValues": null,
        "possibleTypes": null
      },
      {
        "kind": "OBJECT",
        "name": "Query",
        "description": "",
        "fields": [
          {
            "name": "comment",
            "description": "Find a comment by id",
            "args": [
              {
                "name": "id",
                "description": "",
                "type": {
                  "kind": "NON_NULL",
                  "name": null,
                  "ofType": {
                    "kind": "SCALAR",
                    "name": "Long",
                    "ofType": null
                  }
                },
                "defaultValue": null,
                "isDeprecated": false,
                "deprecationReason": null
              }
            ],
            "type": {
              "kind": "OBJECT",
              "name": "Comment",
              "ofType": null
            },
            "isDeprecated": false,
            "deprecationReason": null
          },
          {
            "name": "comments",
            "description": "Find comments",
            "args": [
              {
                "name": "page",
                "description": "",
                "type": {
                  "kind": "INPUT_OBJECT",
                  "name": "InputPage",
                  "ofType": null
                },
                "defaultValue": null,
                "isDeprecated": false,
                "deprecationReason": null
              }
            ],
            "type": {
              "kind": "OBJECT",
              "name": "CommentPageableResponse",
              "ofType": null
            },
            "isDeprecated": false,
            "deprecationReason": null
          },
          {
            "name": "conference",
            "description": "Find a conference based on the name",
            "args": [
              {
                "name": "id",
                "description": "",
                "type": {
                  "kind": "NON_NULL",
                  "name": null,
                  "ofType": {
                    "kind": "SCALAR",
                    "name": "Long",
                    "ofType": null
                  }
                },
                "defaultValue": null,
                "isDeprecated": false,
                "deprecationReason": null
              }
            ],
            "type": {
              "kind": "OBJECT",
              "name": "Conference",
              "ofType": null
            },
            "isDeprecated": false,
            "deprecationReason": null
          },
          {
            "name": "conferences",
            "description": "Find all conferences",
            "args": [
              {
                "name": "filter",
                "description": "",
                "type": {
                  "kind": "INPUT_OBJECT",
                  "name": "InputConference",
                  "ofType": null
                },
                "defaultValue": null,
                "isDeprecated": false,
                "deprecationReason": null
              }
            ],
            "type": {
              "kind": "LIST",
              "name": null,
              "ofType": {
                "kind": "NON_NULL",
                "name": null,
                "ofType": {
                  "kind": "OBJECT",
                  "name": "Conference",
                  "ofType": null
                }
              }
            },
            "isDeprecated": false,
            "deprecationReason": null
          },
          {
            "name": "person",
            "description": "Find a person based by id",
            "args": [
              {
                "name": "id",
                "description": "",
                "type": {
                  "kind": "NON_NULL",
                  "name": null,
                  "ofType": {
                    "kind": "SCALAR",
                    "name": "Long",
                    "ofType": null
                  }
                },
                "defaultValue": null,
                "isDeprecated": false,
                "deprecationReason": null
              }
            ],
            "type": {
              "kind": "OBJECT",
              "name": "Person",
              "ofType": null
            },
            "isDeprecated": false,
            "deprecationReason": null
          },
          {
            "name": "persons",
            "description": "Find all persons, optional search by name",
            "args": [
              {
                "name": "filter",
                "description": "",
                "type": {
                  "kind": "INPUT_OBJECT",
                  "name": "InputPerson",
                  "ofType": null
                },
                "defaultValue": null,
                "isDeprecated": false,
                "deprecationReason": null
              }
            ],
            "type": {
              "kind": "LIST",
              "name": null,
              "ofType": {
                "kind": "NON_NULL",
                "name": null,
                "ofType": {
                  "kind": "OBJECT",
                  "name": "Person",
                  "ofType": null
                }
              }
            },
            "isDeprecated": false,
            "deprecationReason": null
          },
          {
            "name": "talk",
            "description": "Find a talk by id",
            "args": [
              {
                "name": "id",
                "description": "",
                "type": {
                  "kind": "NON_NULL",
                  "name": null,
                  "ofType": {
                    "kind": "SCALAR",
                    "name": "Long",
                    "ofType": null
                  }
                },
                "defaultValue": null,
                "isDeprecated": false,
                "deprecationReason": null
              }
            ],
            "type": {
              "kind": "OBJECT",
              "name": "Talk",
              "ofType": null
            },
            "isDeprecated": false,
            "deprecationReason": null
          },
          {
            "name": "talks",
            "description": "Find all talks",
            "args": [
              {
                "name": "filter",
                "description": "",
                "type": {
                  "kind": "INPUT_OBJECT",
                  "name": "InputTalk",
                  "ofType": null
                },
                "defaultValue": null,
                "isDeprecated": false,
                "deprecationReason": null
              }
            ],
            "type": {
              "kind": "LIST",
              "name": null,
              "ofType": {
                "kind": "NON_NULL",
                "name": null,
                "ofType": {
                  "kind": "OBJECT",
                  "name": "Talk",
                  "ofType": null
                }
              }
            },
            "isDeprecated": false,
            "deprecationReason": null
          }
        ],
        "inputFields": null,
        "interfaces": [],
        "enumValues": null,
        "possibleTypes": null
      },
      {
        "kind": "SCALAR",
        "name": "String",
        "description": "The `String` scalar type represents textual data, represented as UTF-8 character sequences. The String type is most often used by GraphQL to represent free-form human-readable text.",
        "fields": null,
        "inputFields": null,
        "interfaces": null,
        "enumValues": null,
        "possibleTypes": null
      },
      {
        "kind": "OBJECT",
        "name": "Subscription",
        "description": "",
        "fields": [
          {
            "name": "comments",
            "description": "Subscribe to all new comments",
            "args": [],
            "type": {
              "kind": "NON_NULL",
              "name": null,
              "ofType": {
                "kind": "OBJECT",
                "name": "Comment",
                "ofType": null
              }
            },
            "isDeprecated": false,
            "deprecationReason": null
          }
        ],
        "inputFields": null,
        "interfaces": [],
        "enumValues": null,
        "possibleTypes": null
      },
      {
        "kind": "OBJECT",
        "name": "Talk",
        "description": "Object to represent a talk",
        "fields": [
          {
            "name": "conferences",
            "description": "Conferences where the talk is on the agenda",
            "args": [],
            "type": {
              "kind": "LIST",
              "name": null,
              "ofType": {
                "kind": "NON_NULL",
                "name": null,
                "ofType": {
                  "kind": "OBJECT",
                  "name": "Conference",
                  "ofType": null
                }
              }
            },
            "isDeprecated": false,
            "deprecationReason": null
          },
          {
            "name": "id",
            "description": "The technical id",
            "args": [],
            "type": {
              "kind": "NON_NULL",
              "name": null,
              "ofType": {
                "kind": "SCALAR",
                "name": "ID",
                "ofType": null
              }
            },
            "isDeprecated": false,
            "deprecationReason": null
          },
          {
            "name": "speakers",
            "description": "Speakers of the talk",
            "args": [],
            "type": {
              "kind": "LIST",
              "name": null,
              "ofType": {
                "kind": "NON_NULL",
                "name": null,
                "ofType": {
                  "kind": "OBJECT",
                  "name": "Person",
                  "ofType": null
                }
              }
            },
            "isDeprecated": false,
            "deprecationReason": null
          },
          {
            "name": "summary",
            "description": "Short summary of the talk",
            "args": [],
            "type": {
              "kind": "SCALAR",
              "name": "String",
              "ofType": null
            },
            "isDeprecated": false,
            "deprecationReason": null
          },
          {
            "name": "title",
            "description": "Title of the talk",
            "args": [],
            "type": {
              "kind": "NON_NULL",
              "name": null,
              "ofType": {
                "kind": "SCALAR",
                "name": "String",
                "ofType": null
              }
            },
            "isDeprecated": false,
            "deprecationReason": null
          }
        ],
        "inputFields": null,
        "interfaces": [],
        "enumValues": null,
        "possibleTypes": null
      },
      {
        "kind": "OBJECT",
        "name": "__Directive",
        "description": "A Directive provides a way to describe alternate runtime execution and type validation behavior in a GraphQL document.\n\nIn some cases, you need to provide options to alter GraphQL's execution behavior in ways field arguments will not suffice, such as conditionally including or skipping a field. Directives provide this by describing additional information to the executor.",
        "fields": [
          {
            "name": "name",
            "description": null,
            "args": [],
            "type": {
              "kind": "NON_NULL",
              "name": null,
              "ofType": {
                "kind": "SCALAR",
                "name": "String",
                "ofType": null
              }
            },
            "isDeprecated": false,
            "deprecationReason": null
          },
          {
            "name": "description",
            "description": null,
            "args": [],
            "type": {
              "kind": "SCALAR",
              "name": "String",
              "ofType": null
            },
            "isDeprecated": false,
            "deprecationReason": null
          },
          {
            "name": "isRepeatable",
            "description": null,
            "args": [],
            "type": {
              "kind": "NON_NULL",
              "name": null,
              "ofType": {
                "kind": "SCALAR",
                "name": "Boolean",
                "ofType": null
              }
            },
            "isDeprecated": false,
            "deprecationReason": null
          },
          {
            "name": "locations",
            "description": null,
            "args": [],
            "type": {
              "kind": "NON_NULL",
              "name": null,
              "ofType": {
                "kind": "LIST",
                "name": null,
                "ofType": {
                  "kind": "NON_NULL",
                  "name": null,
                  "ofType": {
                    "kind": "ENUM",
                    "name": "__DirectiveLocation",
                    "ofType": null
                  }
                }
              }
            },
            "isDeprecated": false,
            "deprecationReason": null
          },
          {
            "name": "args",
            "description": null,
            "args": [
              {
                "name": "includeDeprecated",
                "description": null,
                "type": {
                  "kind": "SCALAR",
                  "name": "Boolean",
                  "ofType": null
                },
                "defaultValue": "false",
                "isDeprecated": false,
                "deprecationReason": null
              }
            ],
            "type": {
              "kind": "NON_NULL",
              "name": null,
              "ofType": {
                "kind": "LIST",
                "name": null,
                "ofType": {
                  "kind": "NON_NULL",
                  "name": null,
                  "ofType": {
                    "kind": "OBJECT",
                    "name": "__InputValue",
                    "ofType": null
                  }
                }
              }
            },
            "isDeprecated": false,
            "deprecationReason": null
          }
        ],
        "inputFields": null,
        "interfaces": [],
        "enumValues": null,
        "possibleTypes": null
      },
      {
        "kind": "ENUM",
        "name": "__DirectiveLocation",
        "description": "A Directive can be adjacent to many parts of the GraphQL language, a __DirectiveLocation describes one such possible adjacencies.",
        "fields": null,
        "inputFields": null,
        "interfaces": null,
        "enumValues": [
          {
            "name": "QUERY",
            "description": "Location adjacent to a query operation.",
            "isDeprecated": false,
            "deprecationReason": null
          },
          {
            "name": "MUTATION",
            "description": "Location adjacent to a mutation operation.",
            "isDeprecated": false,
            "deprecationReason": null
          },
          {
            "name": "SUBSCRIPTION",
            "description": "Location adjacent to a subscription operation.",
            "isDeprecated": false,
            "deprecationReason": null
          },
          {
            "name": "FIELD",
            "description": "Location adjacent to a field.",
            "isDeprecated": false,
            "deprecationReason": null
          },
          {
            "name": "FRAGMENT_DEFINITION",
            "description": "Location adjacent to a fragment definition.",
            "isDeprecated": false,
            "deprecationReason": null
          },
          {
            "name": "FRAGMENT_SPREAD",
            "description": "Location adjacent to a fragment spread.",
            "isDeprecated": false,
            "deprecationReason": null
          },
          {
            "name": "INLINE_FRAGMENT",
            "description": "Location adjacent to an inline fragment.",
            "isDeprecated": false,
            "deprecationReason": null
          },
          {
            "name": "VARIABLE_DEFINITION",
            "description": "Location adjacent to a variable definition.",
            "isDeprecated": false,
            "deprecationReason": null
          },
          {
            "name": "SCHEMA",
            "description": "Location adjacent to a schema definition.",
            "isDeprecated": false,
            "deprecationReason": null
          },
          {
            "name": "SCALAR",
            "description": "Location adjacent to a scalar definition.",
            "isDeprecated": false,
            "deprecationReason": null
          },
          {
            "name": "OBJECT",
            "description": "Location adjacent to an object type definition.",
            "isDeprecated": false,
            "deprecationReason": null
          },
          {
            "name": "FIELD_DEFINITION",
            "description": "Location adjacent to a field definition.",
            "isDeprecated": false,
            "deprecationReason": null
          },
          {
            "name": "ARGUMENT_DEFINITION",
            "description": "Location adjacent to an argument definition.",
            "isDeprecated": false,
            "deprecationReason": null
          },
          {
            "name": "INTERFACE",
            "description": "Location adjacent to an interface definition.",
            "isDeprecated": false,
            "deprecationReason": null
          },
          {
            "name": "UNION",
            "description": "Location adjacent to a union definition.",
            "isDeprecated": false,
            "deprecationReason": null
          },
          {
            "name": "ENUM",
            "description": "Location adjacent to an enum definition.",
            "isDeprecated": false,
            "deprecationReason": null
          },
          {
            "name": "ENUM_VALUE",
            "description": "Location adjacent to an enum value definition.",
            "isDeprecated": false,
            "deprecationReason": null
          },
          {
            "name": "INPUT_OBJECT",
            "description": "Location adjacent to an input object type definition.",
            "isDeprecated": false,
            "deprecationReason": null
          },
          {
            "name": "INPUT_FIELD_DEFINITION",
            "description": "Location adjacent to an input object field definition.",
            "isDeprecated": false,
            "deprecationReason": null
          }
        ],
        "possibleTypes": null
      },
      {
        "kind": "OBJECT",
        "name": "__EnumValue",
        "description": "One possible value for a given Enum. Enum values are unique values, not a placeholder for a string or numeric value. However an Enum value is returned in a JSON response as a string.",
        "fields": [
          {
            "name": "name",
            "description": null,
            "args": [],
            "type": {
              "kind": "NON_NULL",
              "name": null,
              "ofType": {
                "kind": "SCALAR",
                "name": "String",
                "ofType": null
              }
            },
            "isDeprecated": false,
            "deprecationReason": null
          },
          {
            "name": "description",
            "description": null,
            "args": [],
            "type": {
              "kind": "SCALAR",
              "name": "String",
              "ofType": null
            },
            "isDeprecated": false,
            "deprecationReason": null
          },
          {
            "name": "isDeprecated",
            "description": null,
            "args": [],
            "type": {
              "kind": "NON_NULL",
              "name": null,
              "ofType": {
                "kind": "SCALAR",
                "name": "Boolean",
                "ofType": null
              }
            },
            "isDeprecated": false,
            "deprecationReason": null
          },
          {
            "name": "deprecationReason",
            "description": null,
            "args": [],
            "type": {
              "kind": "SCALAR",
              "name": "String",
              "ofType": null
            },
            "isDeprecated": false,
            "deprecationReason": null
          }
        ],
        "inputFields": null,
        "interfaces": [],
        "enumValues": null,
        "possibleTypes": null
      },
      {
        "kind": "OBJECT",
        "name": "__Field",
        "description": "Object and Interface types are described by a list of Fields, each of which has a name, potentially a list of arguments, and a return type.",
        "fields": [
          {
            "name": "name",
            "description": null,
            "args": [],
            "type": {
              "kind": "NON_NULL",
              "name": null,
              "ofType": {
                "kind": "SCALAR",
                "name": "String",
                "ofType": null
              }
            },
            "isDeprecated": false,
            "deprecationReason": null
          },
          {
            "name": "description",
            "description": null,
            "args": [],
            "type": {
              "kind": "SCALAR",
              "name": "String",
              "ofType": null
            },
            "isDeprecated": false,
            "deprecationReason": null
          },
          {
            "name": "args",
            "description": null,
            "args": [
              {
                "name": "includeDeprecated",
                "description": null,
                "type": {
                  "kind": "SCALAR",
                  "name": "Boolean",
                  "ofType": null
                },
                "defaultValue": "false",
                "isDeprecated": false,
                "deprecationReason": null
              }
            ],
            "type": {
              "kind": "NON_NULL",
              "name": null,
              "ofType": {
                "kind": "LIST",
                "name": null,
                "ofType": {
                  "kind": "NON_NULL",
                  "name": null,
                  "ofType": {
                    "kind": "OBJECT",
                    "name": "__InputValue",
                    "ofType": null
                  }
                }
              }
            },
            "isDeprecated": false,
            "deprecationReason": null
          },
          {
            "name": "type",
            "description": null,
            "args": [],
            "type": {
              "kind": "NON_NULL",
              "name": null,
              "ofType": {
                "kind": "OBJECT",
                "name": "__Type",
                "ofType": null
              }
            },
            "isDeprecated": false,
            "deprecationReason": null
          },
          {
            "name": "isDeprecated",
            "description": null,
            "args": [],
            "type": {
              "kind": "NON_NULL",
              "name": null,
              "ofType": {
                "kind": "SCALAR",
                "name": "Boolean",
                "ofType": null
              }
            },
            "isDeprecated": false,
            "deprecationReason": null
          },
          {
            "name": "deprecationReason",
            "description": null,
            "args": [],
            "type": {
              "kind": "SCALAR",
              "name": "String",
              "ofType": null
            },
            "isDeprecated": false,
            "deprecationReason": null
          }
        ],
        "inputFields": null,
        "interfaces": [],
        "enumValues": null,
        "possibleTypes": null
      },
      {
        "kind": "OBJECT",
        "name": "__InputValue",
        "description": "Arguments provided to Fields or Directives and the input fields of an InputObject are represented as Input Values which describe their type and optionally a default value.",
        "fields": [
          {
            "name": "name",
            "description": null,
            "args": [],
            "type": {
              "kind": "NON_NULL",
              "name": null,
              "ofType": {
                "kind": "SCALAR",
                "name": "String",
                "ofType": null
              }
            },
            "isDeprecated": false,
            "deprecationReason": null
          },
          {
            "name": "description",
            "description": null,
            "args": [],
            "type": {
              "kind": "SCALAR",
              "name": "String",
              "ofType": null
            },
            "isDeprecated": false,
            "deprecationReason": null
          },
          {
            "name": "type",
            "description": null,
            "args": [],
            "type": {
              "kind": "NON_NULL",
              "name": null,
              "ofType": {
                "kind": "OBJECT",
                "name": "__Type",
                "ofType": null
              }
            },
            "isDeprecated": false,
            "deprecationReason": null
          },
          {
            "name": "defaultValue",
            "description": "A GraphQL-formatted string representing the default value for this input value.",
            "args": [],
            "type": {
              "kind": "SCALAR",
              "name": "String",
              "ofType": null
            },
            "isDeprecated": false,
            "deprecationReason": null
          },
          {
            "name": "isDeprecated",
            "description": null,
            "args": [],
            "type": {
              "kind": "NON_NULL",
              "name": null,
              "ofType": {
                "kind": "SCALAR",
                "name": "Boolean",
                "ofType": null
              }
            },
            "isDeprecated": false,
            "deprecationReason": null
          },
          {
            "name": "deprecationReason",
            "description": null,
            "args": [],
            "type": {
              "kind": "SCALAR",
              "name": "String",
              "ofType": null
            },
            "isDeprecated": false,
            "deprecationReason": null
          }
        ],
        "inputFields": null,
        "interfaces": [],
        "enumValues": null,
        "possibleTypes": null
      },
      {
        "kind": "OBJECT",
        "name": "__Schema",
        "description": "A GraphQL Schema defines the capabilities of a GraphQL server. It exposes all available types and directives on the server, as well as the entry points for query, mutation, and subscription operations.",
        "fields": [
          {
            "name": "description",
            "description": null,
            "args": [],
            "type": {
              "kind": "SCALAR",
              "name": "String",
              "ofType": null
            },
            "isDeprecated": false,
            "deprecationReason": null
          },
          {
            "name": "types",
            "description": "A list of all types supported by this server.",
            "args": [],
            "type": {
              "kind": "NON_NULL",
              "name": null,
              "ofType": {
                "kind": "LIST",
                "name": null,
                "ofType": {
                  "kind": "NON_NULL",
                  "name": null,
                  "ofType": {
                    "kind": "OBJECT",
                    "name": "__Type",
                    "ofType": null
                  }
                }
              }
            },
            "isDeprecated": false,
            "deprecationReason": null
          },
          {
            "name": "queryType",
            "description": "The type that query operations will be rooted at.",
            "args": [],
            "type": {
              "kind": "NON_NULL",
              "name": null,
              "ofType": {
                "kind": "OBJECT",
                "name": "__Type",
                "ofType": null
              }
            },
            "isDeprecated": false,
            "deprecationReason": null
          },
          {
            "name": "mutationType",
            "description": "If this server supports mutation, the type that mutation operations will be rooted at.",
            "args": [],
            "type": {
              "kind": "OBJECT",
              "name": "__Type",
              "ofType": null
            },
            "isDeprecated": false,
            "deprecationReason": null
          },
          {
            "name": "subscriptionType",
            "description": "If this server support subscription, the type that subscription operations will be rooted at.",
            "args": [],
            "type": {
              "kind": "OBJECT",
              "name": "__Type",
              "ofType": null
            },
            "isDeprecated": false,
            "deprecationReason": null
          },
          {
            "name": "directives",
            "description": "A list of all directives supported by this server.",
            "args": [],
            "type": {
              "kind": "NON_NULL",
              "name": null,
              "ofType": {
                "kind": "LIST",
                "name": null,
                "ofType": {
                  "kind": "NON_NULL",
                  "name": null,
                  "ofType": {
                    "kind": "OBJECT",
                    "name": "__Directive",
                    "ofType": null
                  }
                }
              }
            },
            "isDeprecated": false,
            "deprecationReason": null
          }
        ],
        "inputFields": null,
        "interfaces": [],
        "enumValues": null,
        "possibleTypes": null
      },
      {
        "kind": "OBJECT",
        "name": "__Type",
        "description": "The fundamental unit of any GraphQL Schema is the type. There are many kinds of types in GraphQL as represented by the `__TypeKind` enum.\n\nDepending on the kind of a type, certain fields describe information about that type. Scalar types provide no information beyond a name, description and optional `specifiedByURL`, while Enum types provide their values. Object and Interface types provide the fields they describe. Abstract types, Union and Interface, provide the Object types possible at runtime. List and NonNull types compose other types.",
        "fields": [
          {
            "name": "kind",
            "description": null,
            "args": [],
            "type": {
              "kind": "NON_NULL",
              "name": null,
              "ofType": {
                "kind": "ENUM",
                "name": "__TypeKind",
                "ofType": null
              }
            },
            "isDeprecated": false,
            "deprecationReason": null
          },
          {
            "name": "name",
            "description": null,
            "args": [],
            "type": {
              "kind": "SCALAR",
              "name": "String",
              "ofType": null
            },
            "isDeprecated": false,
            "deprecationReason": null
          },
          {
            "name": "description",
            "description": null,
            "args": [],
            "type": {
              "kind": "SCALAR",
              "name": "String",
              "ofType": null
            },
            "isDeprecated": false,
            "deprecationReason": null
          },
          {
            "name": "specifiedByURL",
            "description": null,
            "args": [],
            "type": {
              "kind": "SCALAR",
              "name": "String",
              "ofType": null
            },
            "isDeprecated": false,
            "deprecationReason": null
          },
          {
            "name": "fields",
            "description": null,
            "args": [
              {
                "name": "includeDeprecated",
                "description": null,
                "type": {
                  "kind": "SCALAR",
                  "name": "Boolean",
                  "ofType": null
                },
                "defaultValue": "false",
                "isDeprecated": false,
                "deprecationReason": null
              }
            ],
            "type": {
              "kind": "LIST",
              "name": null,
              "ofType": {
                "kind": "NON_NULL",
                "name": null,
                "ofType": {
                  "kind": "OBJECT",
                  "name": "__Field",
                  "ofType": null
                }
              }
            },
            "isDeprecated": false,
            "deprecationReason": null
          },
          {
            "name": "interfaces",
            "description": null,
            "args": [],
            "type": {
              "kind": "LIST",
              "name": null,
              "ofType": {
                "kind": "NON_NULL",
                "name": null,
                "ofType": {
                  "kind": "OBJECT",
                  "name": "__Type",
                  "ofType": null
                }
              }
            },
            "isDeprecated": false,
            "deprecationReason": null
          },
          {
            "name": "possibleTypes",
            "description": null,
            "args": [],
            "type": {
              "kind": "LIST",
              "name": null,
              "ofType": {
                "kind": "NON_NULL",
                "name": null,
                "ofType": {
                  "kind": "OBJECT",
                  "name": "__Type",
                  "ofType": null
                }
              }
            },
            "isDeprecated": false,
            "deprecationReason": null
          },
          {
            "name": "enumValues",
            "description": null,
            "args": [
              {
                "name": "includeDeprecated",
                "description": null,
                "type": {
                  "kind": "SCALAR",
                  "name": "Boolean",
                  "ofType": null
                },
                "defaultValue": "false",
                "isDeprecated": false,
                "deprecationReason": null
              }
            ],
            "type": {
              "kind": "LIST",
              "name": null,
              "ofType": {
                "kind": "NON_NULL",
                "name": null,
                "ofType": {
                  "kind": "OBJECT",
                  "name": "__EnumValue",
                  "ofType": null
                }
              }
            },
            "isDeprecated": false,
            "deprecationReason": null
          },
          {
            "name": "inputFields",
            "description": null,
            "args": [
              {
                "name": "includeDeprecated",
                "description": null,
                "type": {
                  "kind": "SCALAR",
                  "name": "Boolean",
                  "ofType": null
                },
                "defaultValue": "false",
                "isDeprecated": false,
                "deprecationReason": null
              }
            ],
            "type": {
              "kind": "LIST",
              "name": null,
              "ofType": {
                "kind": "NON_NULL",
                "name": null,
                "ofType": {
                  "kind": "OBJECT",
                  "name": "__InputValue",
                  "ofType": null
                }
              }
            },
            "isDeprecated": false,
            "deprecationReason": null
          },
          {
            "name": "ofType",
            "description": null,
            "args": [],
            "type": {
              "kind": "OBJECT",
              "name": "__Type",
              "ofType": null
            },
            "isDeprecated": false,
            "deprecationReason": null
          }
        ],
        "inputFields": null,
        "interfaces": [],
        "enumValues": null,
        "possibleTypes": null
      },
      {
        "kind": "ENUM",
        "name": "__TypeKind",
        "description": "An enum describing what kind of type a given `__Type` is.",
        "fields": null,
        "inputFields": null,
        "interfaces": null,
        "enumValues": [
          {
            "name": "SCALAR",
            "description": "Indicates this type is a scalar.",
            "isDeprecated": false,
            "deprecationReason": null
          },
          {
            "name": "OBJECT",
            "description": "Indicates this type is an object. `fields` and `interfaces` are valid fields.",
            "isDeprecated": false,
            "deprecationReason": null
          },
          {
            "name": "INTERFACE",
            "description": "Indicates this type is an interface. `fields`, `interfaces`, and `possibleTypes` are valid fields.",
            "isDeprecated": false,
            "deprecationReason": null
          },
          {
            "name": "UNION",
            "description": "Indicates this type is a union. `possibleTypes` is a valid field.",
            "isDeprecated": false,
            "deprecationReason": null
          },
          {
            "name": "ENUM",
            "description": "Indicates this type is an enum. `enumValues` is a valid field.",
            "isDeprecated": false,
            "deprecationReason": null
          },
          {
            "name": "INPUT_OBJECT",
            "description": "Indicates this type is an input object. `inputFields` is a valid field.",
            "isDeprecated": false,
            "deprecationReason": null
          },
          {
            "name": "LIST",
            "description": "Indicates this type is a list. `ofType` is a valid field.",
            "isDeprecated": false,
            "deprecationReason": null
          },
          {
            "name": "NON_NULL",
            "description": "Indicates this type is a non-null. `ofType` is a valid field.",
            "isDeprecated": false,
            "deprecationReason": null
          }
        ],
        "possibleTypes": null
      }
    ],
    "directives": [
      {
        "name": "include",
        "description": "Directs the executor to include this field or fragment only when the `if` argument is true",
        "isRepeatable": false,
        "locations": [
          "FIELD",
          "FRAGMENT_SPREAD",
          "INLINE_FRAGMENT"
        ],
        "args": [
          {
            "name": "if",
            "description": "Included when true.",
            "type": {
              "kind": "NON_NULL",
              "name": null,
              "ofType": {
                "kind": "SCALAR",
                "name": "Boolean",
                "ofType": null
              }
            },
            "defaultValue": null,
            "isDeprecated": false,
            "deprecationReason": null
          }
        ]
      },
      {
        "name": "skip",
        "description": "Directs the executor to skip this field or fragment when the `if`'argument is true.",
        "isRepeatable": false,
        "locations": [
          "FIELD",
          "FRAGMENT_SPREAD",
          "INLINE_FRAGMENT"
        ],
        "args": [
          {
            "name": "if",
            "description": "Skipped when true.",
            "type": {
              "kind": "NON_NULL",
              "name": null,
              "ofType": {
                "kind": "SCALAR",
                "name": "Boolean",
                "ofType": null
              }
            },
            "defaultValue": null,
            "isDeprecated": false,
            "deprecationReason": null
          }
        ]
      }
    ]
  }
}